spam_classifier/__init__.py
spam_classifier/data/__init__.py
spam_classifier/data/make_dataset.py
spam_classifier/features/__init__.py
spam_classifier/features/build_features.py
spam_classifier/models/__init__.py
spam_classifier/models/predict_model.py
spam_classifier/models/train_model.py
spam_classifier/models/artefacts/count_vector.pkl
spam_classifier/models/artefacts/naive_bayes.pkl
spam_classifier/visualization/__init__.py
spam_classifier/visualization/visualize.py
tests/__init__.py
tests/main.py
spamBhk-0.0.1.dist-info/LICENSE
spamBhk-0.0.1.dist-info/METADATA
spamBhk-0.0.1.dist-info/WHEEL
spamBhk-0.0.1.dist-info/top_level.txt
spamBhk-0.0.1.dist-info/RECORD
