Metadata-Version: 2.1
Name: spamBhk
Version: 0.0.1
Summary: Classifies a text as Spam or Ham
Home-page: https://github.com/bnriiitb/spam-classifier
Author: Bhaskar Kumar
Author-email: xyz@gmail.com
License: MIT
Platform: UNKNOWN
Classifier: License :: OSI Approved :: MIT License
Classifier: Programming Language :: Python :: 3
Classifier: Programming Language :: Python :: 3.7
Classifier: Programming Language :: Python :: 3.8
License-File: LICENSE
Requires-Dist: pandas
Requires-Dist: scikit-learn (>=1.0.1)
